README.rst
setup.py
aws_service/config.py
aws_service_config.egg-info/PKG-INFO
aws_service_config.egg-info/SOURCES.txt
aws_service_config.egg-info/dependency_links.txt
aws_service_config.egg-info/requires.txt
aws_service_config.egg-info/top_level.txt